hackMiami/__init__.py
hackmiami-69.69.69.dist-info/METADATA
hackmiami-69.69.69.dist-info/WHEEL
hackmiami-69.69.69.dist-info/top_level.txt
hackmiami-69.69.69.dist-info/RECORD
