Metadata-Version: 2.4
Name: hackMiami
Version: 69.69.69
Summary: External malicious demo package
Author-email: s0merset7 <s0merset7@protonmail.com>
Requires-Python: >=3.7
